genice_bondtwist/__init__.py
genice_bondtwist/formats/__init__.py
genice_bondtwist/formats/bondtwist.py
genice_bondtwist/formats/bondtwist2.py
genice_bondtwist/formats/bondtwist3.py
genice_bondtwist/formats/colorchart.py
genice_bondtwist-0.3.dist-info/METADATA
genice_bondtwist-0.3.dist-info/RECORD
genice_bondtwist-0.3.dist-info/WHEEL
genice_bondtwist-0.3.dist-info/entry_points.txt
genice_bondtwist-0.3.dist-info/top_level.txt
