Metadata-Version: 2.1
Name: genice-bondtwist
Version: 0.3
Summary: Bondtwist analysis plugin for GenIce.
Home-page: https://github.com/vitroid/genice-bondtwist/
Author: Masakazu Matsumoto
Author-email: vitroid@gmail.com
License: MIT
Keywords: genice,chirality
Platform: UNKNOWN
Classifier: Development Status :: 4 - Beta
Classifier: Intended Audience :: Developers
Classifier: Programming Language :: Python
Classifier: Programming Language :: Python :: 3.5
Requires-Dist: genice (>=0.23)
Requires-Dist: genice-svg
